flytekitplugins_neptune-1.16.12-py3.14-nspkg.pth
flytekitplugins/neptune/__init__.py
flytekitplugins/neptune/scale_tracking.py
flytekitplugins/neptune/tracking.py
flytekitplugins_neptune-1.16.12.dist-info/METADATA
flytekitplugins_neptune-1.16.12.dist-info/WHEEL
flytekitplugins_neptune-1.16.12.dist-info/namespace_packages.txt
flytekitplugins_neptune-1.16.12.dist-info/top_level.txt
flytekitplugins_neptune-1.16.12.dist-info/RECORD
